Metadata-Version: 2.1
Name: typed-environ
Version: 1.0.1
Summary: Load environment variables with types
Home-page: https://github.com/MichaelKim0407/typed-environ
Author: Michael Kim
Author-email: mkim0470@gmail.com
License: MIT
Platform: UNKNOWN
Classifier: Intended Audience :: Developers
Classifier: License :: OSI Approved :: MIT License
Classifier: Programming Language :: Python
Classifier: Programming Language :: Python :: 2
Classifier: Programming Language :: Python :: 3
Classifier: Topic :: Software Development :: Libraries
Provides-Extra: dev
Provides-Extra: ci
Provides-Extra: test
